{
  "name": "COLLIS RES (JAMES)",
  "address": "61886 BUNKER HILL CT, BEND, OR 97702",
  "hoa": "",
  "nadir_raw": "https://maps.googleapis.com/maps/api/staticmap?center=44.048015,-121.352739&zoom=19&size=640x640&maptype=satellite&key=AIzaSyBodCoZXT1xsVY_erI_cT1XGoWeBm6bx_I",
  "fr": {
    "nadir_url": "",
    "elements": [
      {
        "label": "Main Building",
        "lat": 44.0480771,
        "lng": -121.3527819
      },
      {
        "label": "Landscaped Area",
        "lat": 44.0482013,
        "lng": -121.3526961
      },
      {
        "label": "Outdoor Gathering Area",
        "lat": 44.0479529,
        "lng": -121.3525673
      },
      {
        "label": "Pool Area",
        "lat": 44.0479218,
        "lng": -121.3524815
      }
    ],
    "considerations": [
      {
        "label": "Dense Vegetation",
        "lat": 44.0482013,
        "lng": -121.3528677
      },
      {
        "label": "Limited Rear Access",
        "lat": 44.0478908,
        "lng": -121.352739
      }
    ],
    "recommendations": "Improving emergency response effectiveness on the property could be achieved by addressing the dense vegetation and the limited rear access. Thinning out the vegetation, particularly near access routes, may enhance responder visibility and movement, facilitating faster and safer traversing of the property. Additionally, creating or improving rear access pathways would support responder navigation and allow for more efficient emergency operations, particularly in areas that are difficult to reach from the main entrance. Ensuring that pathways around the main building, landscaped area, outdoor gathering area, and pool are unobstructed and clearly marked could further assist emergency personnel in quickly locating and responding to incidents, enhancing the overall emergency response efficacy."
  },
  "wildfire": {
    "nadir_url": "",
    "conditions": [
      {
        "label": "Scattered Trees",
        "lat": 44.0481392,
        "lng": -121.3529536
      },
      {
        "label": "Vegetation Adjacent to Structure",
        "lat": 44.048015,
        "lng": -121.3526532
      },
      {
        "label": "Scattered Shrubs",
        "lat": 44.0478908,
        "lng": -121.3525673
      },
      {
        "label": "Defensible Space",
        "lat": 44.048015,
        "lng": -121.352739
      }
    ],
    "recommendations": "Enhancing defensible space around the property could be achieved by increasing the separation between vegetation and the structure, especially where vegetation is adjacent to it. Reducing the continuity of fuel by thinning the dense tree canopy and managing the scattered shrubs may further contribute to fuel reduction. Maintaining the existing defensible space while ensuring that scattered trees are adequately spaced can help break potential pathways for fire spread. Addressing the vegetated perimeter with careful management and possible thinning could provide additional protection by creating a more defined buffer zone. Regular maintenance of these areas, combined with strategic vegetation management, may enhance long-term wildfire resilience and support future suppression efforts by improving firefighter access and maneuverability."
  },
  "lat": 44.048015,
  "lng": -121.352739
}