{
  "name": "Highlands 44",
  "address": "19140 Macalpine Loop, Bend, OR 97702",
  "hoa": "highlands",
  "nadir_raw": "https://maps.googleapis.com/maps/api/staticmap?center=44.0517219,-121.3679157&zoom=18&size=640x640&maptype=satellite&key=AIzaSyBodCoZXT1xsVY_erI_cT1XGoWeBm6bx_I",
  "fr": {
    "nadir_url": "https://maps.googleapis.com/maps/api/staticmap?center=44.0517219,-121.3679157&zoom=18&size=640x640&maptype=satellite&markers=color:green|label:1|44.0517219,-121.3679157&markers=color:green|label:2|44.0516722,-121.3678470&markers=color:green|label:3|44.0513493,-121.3674007&markers=color:green|label:4|44.0518461,-121.3680874&markers=color:green|label:5|44.0514735,-121.3682590&markers=color:red|label:A|44.0512251,-121.3672977&markers=color:red|label:B|44.0515977,-121.3677440&key=AIzaSyBodCoZXT1xsVY_erI_cT1XGoWeBm6bx_I",
    "elements": [
      {
        "label": "Main Building",
        "lat": 44.0517219,
        "lng": -121.3679157
      },
      {
        "label": "Front Driveway",
        "lat": 44.0516598,
        "lng": -121.3674007
      },
      {
        "label": "Landscaped Area",
        "lat": 44.0517219,
        "lng": -121.3681732
      },
      {
        "label": "Open Green Space",
        "lat": 44.0518461,
        "lng": -121.368259
      },
      {
        "label": "Perimeter Fencing",
        "lat": 44.0512251,
        "lng": -121.3679157
      }
    ],
    "considerations": [
      {
        "label": "Single Access Point",
        "lat": 44.0515977,
        "lng": -121.3672291
      },
      {
        "label": "Open Terrain",
        "lat": 44.0522187,
        "lng": -121.3686023
      }
    ],
    "recommendations": "Improving responder access and overall response capabilities might be achieved by optimizing the single access point to ensure unobstructed entry and exit for emergency vehicles. This could involve widening the entrance, clearly marking it with reflective signage, and ensuring it's easily visible from the main road. The open terrain, coupled with well-maintained landscaped areas and open green space, may support efficient staging and maneuvering of emergency responders, as they would have ample space to position vehicles and equipment. Enhancing the visibility of the main building from different angles could further assist navigation and situational awareness during emergency operations. Lastly, ensuring that the perimeter fencing does not impede responder movement or create unnecessary barriers would support seamless access and movement throughout the property."
  },
  "wildfire": {
    "nadir_url": "https://maps.googleapis.com/maps/api/staticmap?center=44.0517219,-121.3679157&zoom=18&size=640x640&maptype=satellite&markers=color:orange|label:1|44.0517219,-121.3679157&markers=color:orange|label:2|44.0514238,-121.3677097&markers=color:orange|label:3|44.0512251,-121.3680874&markers=color:orange|label:4|44.0517716,-121.3678470&markers=color:orange|label:5|44.0511009,-121.3674007&markers=color:orange|label:6|44.0516722,-121.3679157&markers=color:orange|label:7|44.0512748,-121.3676410&markers=color:orange|label:8|44.0514735,-121.3681904&markers=color:orange|label:9|44.0513493,-121.3677784&markers=color:orange|label:0|44.0516474,-121.3679157&key=AIzaSyBodCoZXT1xsVY_erI_cT1XGoWeBm6bx_I",
    "conditions": [
      {
        "label": "Scattered Shrubs",
        "lat": 44.0519703,
        "lng": -121.3680874
      },
      {
        "label": "Open Terrain",
        "lat": 44.0520945,
        "lng": -121.367744
      },
      {
        "label": "Vegetated Perimeter",
        "lat": 44.0514114,
        "lng": -121.3685165
      },
      {
        "label": "Defensible Space",
        "lat": 44.0516598,
        "lng": -121.3678299
      },
      {
        "label": "Vegetation Adjacent to Structure",
        "lat": 44.0517467,
        "lng": -121.3678814
      },
      {
        "label": "Open Fuel Break",
        "lat": 44.0515977,
        "lng": -121.3679157
      },
      {
        "label": "Vegetated Access Route",
        "lat": 44.0515356,
        "lng": -121.3673149
      },
      {
        "label": "Scattered Trees",
        "lat": 44.0518461,
        "lng": -121.368259
      }
    ],
    "recommendations": "Enhancing defensible space by increasing the separation between vegetation and structures, particularly where vegetation is currently adjacent to the buildings, could improve the property's resilience against wildfires. Maintaining the condition of the open fuel break while ensuring that scattered shrubs and trees within the surrounding landscape are managed to minimize fuel continuity may further support suppression efforts. Clearing excess vegetation along the access route could improve firefighter access and roadway visibility. Preserving open areas and ensuring the vegetated perimeter does not connect directly with structures may help in reducing potential fire spread. Consistent management of the scattered trees can sustain an effective buffer zone, contributing to long-term vegetation management and helping to maintain the property's preparedness in the face of potential wildfire events."
  },
  "lat": 44.0517219,
  "lng": -121.3679157
}