{
  "name": "DANIELSON RES (RICHARD &CAROL)",
  "address": "20396 BUTTERMILK, BEND, OR 97702",
  "hoa": "",
  "nadir_raw": "https://maps.googleapis.com/maps/api/staticmap?center=44.0079825,-121.3039246&zoom=19&size=640x640&maptype=satellite&key=AIzaSyBodCoZXT1xsVY_erI_cT1XGoWeBm6bx_I",
  "fr": {
    "nadir_url": "",
    "elements": [
      {
        "label": "Main Building",
        "lat": 44.0079825,
        "lng": -121.3039074
      },
      {
        "label": "Front Driveway",
        "lat": 44.0078582,
        "lng": -121.3039418
      },
      {
        "label": "Landscaped Area",
        "lat": 44.0081689,
        "lng": -121.3039246
      },
      {
        "label": "Open Green Space",
        "lat": 44.0081068,
        "lng": -121.3038388
      },
      {
        "label": "Pedestrian Walkways",
        "lat": 44.0079204,
        "lng": -121.3039675
      }
    ],
    "considerations": [
      {
        "label": "Limited Side Access",
        "lat": 44.0079204,
        "lng": -121.3040104
      },
      {
        "label": "Dense Vegetation",
        "lat": 44.0081689,
        "lng": -121.3037959
      }
    ],
    "recommendations": "Enhancing emergency response at the property could benefit from efforts to improve side access by widening pathways or creating additional entry points to facilitate movement around the main building. Thinning dense vegetation along existing walkways and near access routes could enhance visibility and ease navigation for responders. Designating clear emergency staging areas in open green spaces may support effective organization and coordination of response activities, ensuring personnel can quickly assemble and deploy when needed. Maintaining unobstructed driveways and clear pedestrian walkways would support responder staging and equipment transport, contributing to improved overall operational efficiency during critical moments."
  },
  "wildfire": {
    "nadir_url": "",
    "conditions": [
      {
        "label": "Vegetation Adjacent to Structure",
        "lat": 44.0080446,
        "lng": -121.3040104
      },
      {
        "label": "Scattered Trees",
        "lat": 44.0079204,
        "lng": -121.3040963
      },
      {
        "label": "Vegetated Perimeter",
        "lat": 44.0081379,
        "lng": -121.30371
      }
    ],
    "recommendations": "Enhancing defensible space by increasing the separation between the dense tree canopy and the structures could reduce fuel continuity and improve the property's resilience to wildfire exposure. Managing the vegetation adjacent to the structure and access route would support firefighter access and improve suppression efforts. Thinning out or strategically removing some of the tree clusters and scattered trees can decrease the likelihood of fire spread via crown fire pathways. Preserving and potentially expanding open terrain areas as natural fuel breaks could further mitigate the risk of wildfire spread toward the structure. Long-term considerations should include regular maintenance of the vegetated perimeter to sustain an effective buffer zone, thereby supporting ongoing wildfire resilience while maintaining property preparedness."
  },
  "lat": 44.0079825,
  "lng": -121.3039246
}