{
  "name": "ALLISON RES (REX & DAWN)",
  "address": "18790 HAKAMORE DR, BEND, OR 97703",
  "hoa": "",
  "nadir_raw": "https://maps.googleapis.com/maps/api/staticmap?center=44.1028251,-121.3878166&zoom=19&size=640x640&maptype=satellite&key=AIzaSyBodCoZXT1xsVY_erI_cT1XGoWeBm6bx_I",
  "fr": {
    "nadir_url": "",
    "elements": [
      {
        "label": "Main Building",
        "lat": 44.102701,
        "lng": -121.3879883
      },
      {
        "label": "Detached Structure",
        "lat": 44.102701,
        "lng": -121.3873016
      },
      {
        "label": "Pool Area",
        "lat": 44.1028251,
        "lng": -121.3869583
      },
      {
        "label": "Landscaped Area",
        "lat": 44.1033215,
        "lng": -121.3879883
      },
      {
        "label": "Open Green Space",
        "lat": 44.1034456,
        "lng": -121.3886749
      }
    ],
    "considerations": [
      {
        "label": "Multiple Structures",
        "lat": 44.1028251,
        "lng": -121.3878166
      },
      {
        "label": "Dense Vegetation",
        "lat": 44.1033215,
        "lng": -121.3881599
      }
    ],
    "recommendations": "Improving clear access points around the main building and addressing limited rear access might support quicker response times and enhance accessibility for emergency personnel. Managing and reducing dense vegetation, particularly in areas surrounding the pool and open green space, could facilitate improved visibility and unobstructed movement for responders. Designating specific pathways or access routes through the landscaped areas may assist emergency units in navigating the property more effectively. Ensuring that emergency responders can easily identify and access the separate structures like the detached building and tennis court may streamline operational coordination. Overall, strategic planning of clear pathways and routine vegetation management might enhance emergency operations and facilitate efficient staging and movement across the property."
  },
  "wildfire": {
    "nadir_url": "",
    "conditions": [
      {
        "label": "Vegetation Adjacent to Structure",
        "lat": 44.102701,
        "lng": -121.3877823
      },
      {
        "label": "Dense Tree Canopy",
        "lat": 44.1025769,
        "lng": -121.3877136
      },
      {
        "label": "Scattered Trees",
        "lat": 44.1030733,
        "lng": -121.3874733
      },
      {
        "label": "Defensible Space",
        "lat": 44.1028251,
        "lng": -121.3877136
      },
      {
        "label": "Water Feature",
        "lat": 44.1029492,
        "lng": -121.3881599
      },
      {
        "label": "Vegetated Drainage",
        "lat": 44.1033215,
        "lng": -121.38713
      },
      {
        "label": "Structure Cluster",
        "lat": 44.1027755,
        "lng": -121.3878853
      },
      {
        "label": "Surrounding Open Space",
        "lat": 44.1036938,
        "lng": -121.386615
      }
    ],
    "recommendations": "Improving vegetation management adjacent to the structure by increasing separation and reducing dense tree canopy near the building may enhance defensible space. Creating breaks in the tree canopy and managing scattered trees can reduce fuel continuity and create a less continuous pathway for fire. The open terrain around the property presents an opportunity to expand fuel breaks further, potentially increasing the effectiveness of defensible space. The existing tennis court and water feature should be maintained as part of the property’s strategic fuel modification efforts, as these features generally do not contribute to fuel loads and can help limit fire spread. Regular maintenance of the vegetated drainage is advisable to ensure it doesn't become a source of embers. Within the cluster of structures, proper management of vegetation can help reduce exposure, while preserving surrounding open space can continue to improve overall property resilience by acting as a natural barrier and supporting wildfire preparedness."
  },
  "lat": 44.1028251,
  "lng": -121.3878166
}